[
	{
		"fileName": "../../sa/sa181022.mp3"
	},
	{
		"fileName": "../../ka/ka181022.mp3"
	},
	{
		"fileName": "../../fc/fc181022.mp3"
	},
	{
		"fileName": "../../gv/gv181022.mp3"
	},
	{
		"fileName": "../../yu/yu181022.mp3"
	},
	{
		"fileName": "../../bc/bc181022.mp3"
	},
	{
		"fileName": "../../ir/ir181022.mp3"
	},
	{
		"fileName": "../../im/im181022.mp3"
	},
	{
		"fileName": "../../cc/cc181022.mp3"
	},
	{
		"fileName": "../../ib/ib181022.mp3"
	},
	{
		"fileName": "../../pc/pc181022.mp3"
	},
	{
		"fileName": "../../ut/ut181022.mp3"
	},
	{
		"fileName": "../../se/se181022.mp3"
	},
	{
		"fileName": "../../up/up181022.mp3"
	},
	{
		"fileName": "../../hg/hg181022.mp3"
	},
	{
		"fileName": "../../wf/wf181022.mp3"
	},
	{
		"fileName": "../../ug/ug181022.mp3"
	},
	{
		"fileName": "../../tg/tg181022.mp3"
	},
	{
		"fileName": "../../gn/gn181022.mp3"
	},
	{
		"fileName": "../../ee/ee181022.mp3"
	},
	{
		"fileName": "../../mw/mw181022.mp3"
	},
	{
		"fileName": "../../th/th181022.mp3"
	},
	{
		"fileName": "../../be/be181022.mp3"
	},
	{
		"fileName": "../../it/it181022.mp3"
	},
	{
		"fileName": "../../iv/iv181022.mp3"
	},
	{
		"fileName": "../../pb/pb181022.mp3"
	},
	{
		"fileName": "../../ds/ds181022.mp3"
	}
]